widgetron/__init__.py
widgetron/__main__.py
widgetron/args.yml
widgetron/constants.py
widgetron/globals.py
widgetron/parse_args.py
widgetron/icons/widgetron.icns
widgetron/icons/widgetron.ico
widgetron/icons/widgetron.png
widgetron/templates/constructor/post_install.sh_template
widgetron/templates/constructor/Menu/widgetron_shortcut.json_template
widgetron/templates/electron/index.html_template
widgetron/templates/electron/main.js_template
widgetron/templates/electron/package.json_template
widgetron/templates/recipe/recipe.yaml_template
widgetron/templates/server/LICENSE.txt_template
widgetron/templates/server/README.md_template
widgetron/templates/server/setup.cfg_template
widgetron/templates/server/setup.py_template
widgetron/templates/server/widgetron_app/__init__.py_template
widgetron/templates/server/widgetron_app/__main__.pyw_template
widgetron/templates/server/widgetron_app/cli.py_template
widgetron/templates/server/widgetron_app/notebooks/debug.ipynb
widgetron/utils/__init__.py
widgetron/utils/conda.py
widgetron/utils/jinja_functions.py
widgetron/utils/settings.py
widgetron/utils/shell.py
widgetron-0.2.6.dist-info/LICENSE
widgetron-0.2.6.dist-info/METADATA
widgetron-0.2.6.dist-info/WHEEL
widgetron-0.2.6.dist-info/entry_points.txt
widgetron-0.2.6.dist-info/top_level.txt
widgetron-0.2.6.dist-info/RECORD
