Metadata-Version: 2.1
Name: widgetron
Version: 0.2.6
Summary: Application builder for ipython notebooks
Author: Joel Stansbury
License: MIT
Classifier: Programming Language :: Python :: 3
License-File: LICENSE
Requires-Dist: jinja2
Requires-Dist: pyyaml
Requires-Dist: traitlets >=5
